aranet4/__init__.py
aranet4/aranetctl.py
aranet4/client.py
aranet4-2.0.0.dist-info/LICENSE
aranet4-2.0.0.dist-info/METADATA
aranet4-2.0.0.dist-info/WHEEL
aranet4-2.0.0.dist-info/entry_points.txt
aranet4-2.0.0.dist-info/top_level.txt
aranet4-2.0.0.dist-info/RECORD
