Metadata-Version: 2.1
Name: aranet4
Version: 2.0.0
Summary: Aranet4 Python client
Home-page: https://github.com/Anrijs/Aranet4-Python
License: UNKNOWN
Platform: UNKNOWN
Classifier: Programming Language :: Python
Classifier: Programming Language :: Python :: 2.7
Classifier: Programming Language :: Python :: 3
Classifier: License :: OSI Approved :: MIT License
Classifier: Operating System :: OS Independent
Requires-Dist: bleak
Requires-Dist: requests
